XmindExcelTestcases/__init__.py
XmindExcelTestcases/__main__.py
XmindExcelTestcases/convert_xmind_to_excel.py
XmindExcelTestcases-0.0.9.dist-info/LICENSE
XmindExcelTestcases-0.0.9.dist-info/METADATA
XmindExcelTestcases-0.0.9.dist-info/WHEEL
XmindExcelTestcases-0.0.9.dist-info/entry_points.txt
XmindExcelTestcases-0.0.9.dist-info/top_level.txt
XmindExcelTestcases-0.0.9.dist-info/RECORD
