Metadata-Version: 2.1
Name: XmindExcelTestcases
Version: 0.0.9
Summary: xmind脑图转换为Excel格式的测试用例
Home-page: UNKNOWN
Author: kaven.xue
Author-email: 454086662@qq.com
License: UNKNOWN
Platform: UNKNOWN
Classifier: Programming Language :: Python :: 3
Classifier: License :: OSI Approved :: MIT License
Classifier: Operating System :: OS Independent
License-File: LICENSE
